LICENSE
dsimplex/__init__.py
dsimplex/args.py
dsimplex/dsimplex-gui.spec
dsimplex/gui.py
dsimplex/result_head.jinja2
dsimplex/result_tail.jinja2
dsimplex/result_template.jinja2
dsimplex/simplex.py
dsimplex-0.2.0.dist-info/entry_points.txt
dsimplex-0.2.0.dist-info/LICENSE
dsimplex-0.2.0.dist-info/WHEEL
dsimplex-0.2.0.dist-info/METADATA
dsimplex-0.2.0.dist-info/RECORD
