Metadata-Version: 2.1
Name: dsimplex
Version: 0.2.0
Summary: A simplex implementation in python
Home-page: https://github.com/terminaldweller/simplex
License: GPL3
Keywords: simplex,linear-programming,lp
Author: terminaldweller
Author-email: thabogre@gmail.com
Requires-Python: >=3.8,<3.11
Classifier: Environment :: Console
Classifier: License :: Other/Proprietary License
Classifier: Programming Language :: Python :: 3
Classifier: Programming Language :: Python :: 3.10
Classifier: Programming Language :: Python :: 3.8
Classifier: Programming Language :: Python :: 3.9
Requires-Dist: Jinja2 (>=3.1.2,<4.0.0)
Requires-Dist: Markdown (>=3.4.1,<4.0.0)
Requires-Dist: numpy (>=1.22.4,<2.0.0)
Requires-Dist: scipy (>=1.8.1,<2.0.0)
Requires-Dist: tk-html-widgets (>=0.4.0,<0.5.0)
Requires-Dist: ttkthemes (>=3.2.2,<4.0.0)
Project-URL: Repository, https://github.com/terminaldweller/simplex
